MANIFEST.in
README.rst
requirements.txt
setup.cfg
setup.py
boxtree/__init__.py
boxtree/area_query.py
boxtree/array_context.py
boxtree/bounding_box.py
boxtree/constant_one.py
boxtree/cost.py
boxtree/fmm.py
boxtree/pyfmmlib_integration.py
boxtree/rotation_classes.py
boxtree/timing.py
boxtree/tools.py
boxtree/translation_classes.py
boxtree/traversal.py
boxtree/tree.py
boxtree/tree_build.py
boxtree/tree_build_kernels.py
boxtree/tree_of_boxes.py
boxtree/version.py
boxtree/visualization.py
boxtree.egg-info/PKG-INFO
boxtree.egg-info/SOURCES.txt
boxtree.egg-info/dependency_links.txt
boxtree.egg-info/requires.txt
boxtree.egg-info/top_level.txt
boxtree/distributed/__init__.py
boxtree/distributed/calculation.py
boxtree/distributed/local_traversal.py
boxtree/distributed/local_tree.py
boxtree/distributed/partition.py
doc/Makefile
doc/conf.py
doc/cost.rst
doc/distributed.rst
doc/fmm.rst
doc/index.rst
doc/intro.rst
doc/lookup.rst
doc/misc.rst
doc/tools.rst
doc/traversal.rst
doc/tree-build.rst
doc/tree.rst
doc/images/linf-l2.png
doc/images/tree.png
examples/cost_model.py
examples/demo.py
test/test_cost_model.py
test/test_distributed.py
test/test_fmm.py
test/test_tools.py
test/test_traversal.py
test/test_tree.py
test/test_tree_of_boxes.py