Metadata-Version: 2.1
Name: boxtree
Version: 2023.1
Summary: Quadtree/octree building in Python and OpenCL
Home-page: https://documen.tician.de/boxtree/
Author: Andreas Kloeckner
Author-email: inform@tiker.net
License: MIT
Classifier: Development Status :: 3 - Alpha
Classifier: Intended Audience :: Developers
Classifier: Intended Audience :: Other Audience
Classifier: Intended Audience :: Science/Research
Classifier: License :: OSI Approved :: MIT License
Classifier: Natural Language :: English
Classifier: Programming Language :: Python
Classifier: Programming Language :: Python :: 3
Classifier: Topic :: Scientific/Engineering
Classifier: Topic :: Scientific/Engineering :: Information Analysis
Classifier: Topic :: Scientific/Engineering :: Mathematics
Classifier: Topic :: Scientific/Engineering :: Visualization
Classifier: Topic :: Software Development :: Libraries
Classifier: Topic :: Utilities
Requires-Python: ~=3.8
Requires-Dist: Mako>=0.7.3
Requires-Dist: pytools>=2018.4
Requires-Dist: pyopencl>=2018.2.2
Requires-Dist: cgen>=2013.1.2
Requires-Dist: arraycontext>=2021.1
Provides-Extra: test
Requires-Dist: pytest>=2.3; extra == "test"
